huaweicloudsdkdc/__init__.py
huaweicloudsdkdc/v3/__init__.py
huaweicloudsdkdc/v3/dc_async_client.py
huaweicloudsdkdc/v3/dc_client.py
huaweicloudsdkdc/v3/model/__init__.py
huaweicloudsdkdc/v3/model/add_gdgw_route_action.py
huaweicloudsdkdc/v3/model/address_body.py
huaweicloudsdkdc/v3/model/address_family.py
huaweicloudsdkdc/v3/model/band_width_info.py
huaweicloudsdkdc/v3/model/bandwidth_info_external.py
huaweicloudsdkdc/v3/model/base_add_route_action.py
huaweicloudsdkdc/v3/model/base_delete_route_action.py
huaweicloudsdkdc/v3/model/batch_create_resource_tags_request.py
huaweicloudsdkdc/v3/model/batch_create_resource_tags_response.py
huaweicloudsdkdc/v3/model/batch_operate_resource_tags_request_body.py
huaweicloudsdkdc/v3/model/bind_global_eips_request.py
huaweicloudsdkdc/v3/model/bind_global_eips_response.py
huaweicloudsdkdc/v3/model/binding_geip_body.py
huaweicloudsdkdc/v3/model/common_routetable.py
huaweicloudsdkdc/v3/model/connect_gateway_response.py
huaweicloudsdkdc/v3/model/create_binding_geip_request_body.py
huaweicloudsdkdc/v3/model/create_connect_gateway.py
huaweicloudsdkdc/v3/model/create_connect_gateway_request.py
huaweicloudsdkdc/v3/model/create_connect_gateway_request_body.py
huaweicloudsdkdc/v3/model/create_connect_gateway_response.py
huaweicloudsdkdc/v3/model/create_external_peer_link_request_body.py
huaweicloudsdkdc/v3/model/create_external_peer_link_request_body_peer_link.py
huaweicloudsdkdc/v3/model/create_external_peer_link_request_body_peer_link_peer_site.py
huaweicloudsdkdc/v3/model/create_global_dc_gateway.py
huaweicloudsdkdc/v3/model/create_global_dc_gateway_entry.py
huaweicloudsdkdc/v3/model/create_global_dc_gateway_request.py
huaweicloudsdkdc/v3/model/create_global_dc_gateway_request_body.py
huaweicloudsdkdc/v3/model/create_global_dc_gateway_response.py
huaweicloudsdkdc/v3/model/create_hosted_direct_connect.py
huaweicloudsdkdc/v3/model/create_hosted_direct_connect_request.py
huaweicloudsdkdc-3.1.184.dist-info/METADATA
huaweicloudsdkdc-3.1.184.dist-info/WHEEL
huaweicloudsdkdc-3.1.184.dist-info/licenses/LICENSE
huaweicloudsdkdc-3.1.184.dist-info/RECORD
